jasmin_log_decoder-1.0.0.dist-info/licenses/LICENSE
jasmin_sms_decoder/__init__.py
jasmin_sms_decoder/decoder.py
jasmin_log_decoder-1.0.0.dist-info/METADATA
jasmin_log_decoder-1.0.0.dist-info/WHEEL
jasmin_log_decoder-1.0.0.dist-info/entry_points.txt
jasmin_log_decoder-1.0.0.dist-info/top_level.txt
jasmin_log_decoder-1.0.0.dist-info/RECORD
