Metadata-Version: 2.4
Name: jasmin-log-decoder
Version: 1.0.0
Summary: Decode Jasmin SMS Gateway messages from logs
Home-page: https://github.com/pbarabadze/jasmin-log-decoder
Author: Paata Barabadze
Author-email: Paata Barabadze <p.barabadze@gmail.com>
License: MIT
Project-URL: Homepage, https://github.com/pbarabadze/jasmin-log-decoder
Keywords: jasmin,sms,gateway,decode,logs
Classifier: Development Status :: 4 - Beta
Classifier: Intended Audience :: Developers
Classifier: Topic :: Communications :: Telephony
Classifier: License :: OSI Approved :: MIT License
Classifier: Programming Language :: Python :: 3
Requires-Python: >=3.7
License-File: LICENSE
Dynamic: author
Dynamic: home-page
Dynamic: license-file
Dynamic: requires-python
